gmab/__init__.py
gmab/cli.py
gmab/commands/__init__.py
gmab/commands/configure.py
gmab/commands/list.py
gmab/commands/spawn.py
gmab/commands/terminate.py
gmab/providers/__init__.py
gmab/providers/aws.py
gmab/providers/base.py
gmab/providers/hetzner.py
gmab/providers/linode.py
gmab/utils/__init__.py
gmab/utils/config_loader.py
gmab/utils/paths.py
gmab-0.1.4.dist-info/licenses/LICENSE
gmab-0.1.4.dist-info/METADATA
gmab-0.1.4.dist-info/WHEEL
gmab-0.1.4.dist-info/entry_points.txt
gmab-0.1.4.dist-info/top_level.txt
gmab-0.1.4.dist-info/RECORD
