Metadata-Version: 2.4
Name: gmab
Version: 0.1.4
Summary: Give Me A Box - CLI tool to spawn, list, and manage temporary cloud boxes
Author-email: Steve Cannivy <steve@roudeleiw.lu>
License: MIT
Project-URL: Homepage, https://github.com/superfishlu/gmab
Project-URL: Bug Tracker, https://github.com/superfishlu/gmab/issues
Keywords: cloud,cli,devops,aws,linode,hetzner
Classifier: Development Status :: 3 - Alpha
Classifier: Intended Audience :: Developers
Classifier: License :: OSI Approved :: MIT License
Classifier: Operating System :: OS Independent
Classifier: Programming Language :: Python :: 3
Classifier: Programming Language :: Python :: 3.8
Classifier: Programming Language :: Python :: 3.9
Classifier: Programming Language :: Python :: 3.10
Classifier: Programming Language :: Python :: 3.11
Requires-Python: >=3.8
License-File: LICENSE
Requires-Dist: click>=8.0.0
Requires-Dist: requests>=2.28.0
Requires-Dist: boto3>=1.26.0
Dynamic: license-file
